blossom_ai/__init__.py
blossom_ai/_version.py
blossom_ai/client.py
blossom_ai/core/__init__.py
blossom_ai/core/config.py
blossom_ai/core/errors.py
blossom_ai/core/interfaces.py
blossom_ai/core/models.py
blossom_ai/core/session_manager.py
blossom_ai/docs/API_CONFIG.md
blossom_ai/docs/API_IMAGE.md
blossom_ai/docs/API_REFERENCE.md
blossom_ai/docs/API_TEXT.md
blossom_ai/docs/API_VISION.md
blossom_ai/docs/ARCHITECTURE.md
blossom_ai/docs/ASYNC_PATTERNS.md
blossom_ai/docs/BUILDER_PATTERN.md
blossom_ai/docs/CACHING.md
blossom_ai/docs/CELERY.md
blossom_ai/docs/CHANGELOG.md
blossom_ai/docs/CLIENT.md
blossom_ai/docs/CODE_STYLE.md
blossom_ai/docs/CONFIGURATION.md
blossom_ai/docs/CONNECTION_POOLING.md
blossom_ai/docs/CONSENSUS.md
blossom_ai/docs/CONTRIBUTING.md
blossom_ai/docs/CUSTOM_COMPONENTS.md
blossom_ai/docs/DATA_PIPELINE.md
blossom_ai/docs/DEBUGGING.md
blossom_ai/docs/DEPENDENCY_INJECTION.md
blossom_ai/docs/DISCORD_BOT.md
blossom_ai/docs/DOCKER.md
blossom_ai/docs/ERROR_HANDLING.md
blossom_ai/docs/ERROR_TYPES.md
blossom_ai/docs/FACTORY_PATTERN.md
blossom_ai/docs/FASTAPI.md
blossom_ai/docs/FILE_READER.md
blossom_ai/docs/FLASK.md
blossom_ai/docs/FUNCTION_CALLING.md
blossom_ai/docs/GENERATORS.md
blossom_ai/docs/IMAGE_ADVANCED.md
blossom_ai/docs/IMAGE_BATCH.md
blossom_ai/docs/IMAGE_GENERATION.md
blossom_ai/docs/IMAGE_URLS.md
blossom_ai/docs/INDEX.md
blossom_ai/docs/INSTALLATION.md
blossom_ai/docs/JSON_MODE.md
blossom_ai/docs/LINKS.md
blossom_ai/docs/LOGGING.md
blossom_ai/docs/MEMORY.md
blossom_ai/docs/MULTIMODAL_APPS.md
blossom_ai/docs/PERFORMANCE.md
blossom_ai/docs/PROTOCOL_INTERFACES.md
blossom_ai/docs/QUICKSTART.md
blossom_ai/docs/RATE_LIMITING.md
blossom_ai/docs/REASONING.md
blossom_ai/docs/SELF_CORRECTION.md
blossom_ai/docs/SINGLETON_PATTERN.md
blossom_ai/docs/STATUS_CODES.md
blossom_ai/docs/STRATEGY_PATTERN.md
blossom_ai/docs/TELEGRAM_BOT.md
blossom_ai/docs/TESTING.md
blossom_ai/docs/TEXT_ADVANCED.md
blossom_ai/docs/TEXT_GENERATION.md
blossom_ai/docs/TUTORIAL.md
eclips_blossom_ai-0.8.0.dist-info/METADATA
eclips_blossom_ai-0.8.0.dist-info/WHEEL
eclips_blossom_ai-0.8.0.dist-info/licenses/LICENSE
eclips_blossom_ai-0.8.0.dist-info/RECORD
