Metadata-Version: 2.4
Name: eclips-blossom-ai
Version: 0.8.0
Summary: 🌸 Beautiful and simple AI generation library for images, text, and audio
Project-URL: Homepage, https://github.com/PrimeevolutionZ/blossom-ai
Project-URL: Documentation, https://github.com/PrimeevolutionZ/blossom-ai/blob/master/blossom_ai/docs/INDEX.md
Project-URL: Repository, https://github.com/PrimeevolutionZ/blossom-ai
Project-URL: Source Code, https://github.com/PrimeevolutionZ/blossom-ai
Project-URL: Bug Tracker, https://github.com/PrimeevolutionZ/blossom-ai/issues
Project-URL: Issue Tracker, https://github.com/PrimeevolutionZ/blossom-ai/issues
Project-URL: Changelog, https://github.com/PrimeevolutionZ/blossom-ai/blob/master/blossom_ai/docs/CHANGELOG.md
Project-URL: Security Policy, https://github.com/PrimeevolutionZ/blossom-ai/blob/master/SECURITY.md
Author-email: Eclips Team <develop@eclips-team.ru>
Maintainer-email: Eclips Team <develop@eclips-team.ru>
License: MIT
License-File: LICENSE
Keywords: ai,artificial-intelligence,audio-generation,deep-learning,generative-ai,gpt,image-generation,llm,machine-learning,pollinations,stable-diffusion,text-generation,text-to-speech,tts
Classifier: Development Status :: 5 - Production/Stable
Classifier: Intended Audience :: Developers
Classifier: Intended Audience :: Information Technology
Classifier: Intended Audience :: Science/Research
Classifier: License :: OSI Approved :: MIT License
Classifier: Natural Language :: English
Classifier: Natural Language :: Russian
Classifier: Operating System :: OS Independent
Classifier: Programming Language :: Python
Classifier: Programming Language :: Python :: 3
Classifier: Programming Language :: Python :: 3 :: Only
Classifier: Programming Language :: Python :: 3.10
Classifier: Programming Language :: Python :: 3.11
Classifier: Programming Language :: Python :: 3.12
Classifier: Programming Language :: Python :: 3.13
Classifier: Programming Language :: Python :: 3.14
Classifier: Programming Language :: Python :: Implementation :: CPython
Classifier: Topic :: Internet :: WWW/HTTP :: Dynamic Content
Classifier: Topic :: Multimedia :: Graphics
Classifier: Topic :: Multimedia :: Sound/Audio :: Speech
Classifier: Topic :: Scientific/Engineering :: Artificial Intelligence
Classifier: Topic :: Scientific/Engineering :: Image Processing
Classifier: Topic :: Software Development :: Libraries :: Python Modules
Classifier: Typing :: Typed
Requires-Python: >=3.11
Requires-Dist: httpx<1.0.0,>=0.25.0
Requires-Dist: pydantic<3.0.0,>=2.5.0
Requires-Dist: python-dotenv>=1.0.0
Requires-Dist: tenacity<9.1.3,>=9.0.0
Requires-Dist: typing-extensions>=4.5.0; python_version < '3.11'
Provides-Extra: all
Requires-Dist: bandit>=1.7.0; extra == 'all'
Requires-Dist: black>=23.7.0; extra == 'all'
Requires-Dist: mkdocs-gen-files>=0.5.0; extra == 'all'
Requires-Dist: mkdocs-literate-nav>=0.6.0; extra == 'all'
Requires-Dist: mkdocs-material>=9.2.0; extra == 'all'
Requires-Dist: mkdocs-section-index>=0.3.0; extra == 'all'
Requires-Dist: mkdocs>=1.5.0; extra == 'all'
Requires-Dist: mkdocstrings[python]>=0.22.0; extra == 'all'
Requires-Dist: mypy>=1.5.0; extra == 'all'
Requires-Dist: pre-commit>=3.3.0; extra == 'all'
Requires-Dist: pytest-asyncio>=0.21.0; extra == 'all'
Requires-Dist: pytest-cov>=4.1.0; extra == 'all'
Requires-Dist: pytest-mock>=3.11.0; extra == 'all'
Requires-Dist: pytest-timeout>=2.1.0; extra == 'all'
Requires-Dist: pytest>=7.4.0; extra == 'all'
Requires-Dist: python-magic-bin>=0.4.14; (sys_platform == 'win32') and extra == 'all'
Requires-Dist: python-magic>=0.4.27; (sys_platform != 'win32') and extra == 'all'
Requires-Dist: ruff>=0.0.287; extra == 'all'
Requires-Dist: safety>=2.3.0; extra == 'all'
Requires-Dist: structlog>=23.1.0; extra == 'all'
Requires-Dist: types-requests>=2.31.0; extra == 'all'
Provides-Extra: dev
Requires-Dist: bandit>=1.7.0; extra == 'dev'
Requires-Dist: black>=23.7.0; extra == 'dev'
Requires-Dist: mypy>=1.5.0; extra == 'dev'
Requires-Dist: pre-commit>=3.3.0; extra == 'dev'
Requires-Dist: pytest-asyncio>=0.21.0; extra == 'dev'
Requires-Dist: pytest-cov>=4.1.0; extra == 'dev'
Requires-Dist: pytest-mock>=3.11.0; extra == 'dev'
Requires-Dist: pytest-timeout>=2.1.0; extra == 'dev'
Requires-Dist: pytest>=7.4.0; extra == 'dev'
Requires-Dist: ruff>=0.0.287; extra == 'dev'
Requires-Dist: safety>=2.3.0; extra == 'dev'
Requires-Dist: types-requests>=2.31.0; extra == 'dev'
Provides-Extra: docs
Requires-Dist: mkdocs-gen-files>=0.5.0; extra == 'docs'
Requires-Dist: mkdocs-literate-nav>=0.6.0; extra == 'docs'
Requires-Dist: mkdocs-material>=9.2.0; extra == 'docs'
Requires-Dist: mkdocs-section-index>=0.3.0; extra == 'docs'
Requires-Dist: mkdocs>=1.5.0; extra == 'docs'
Requires-Dist: mkdocstrings[python]>=0.22.0; extra == 'docs'
Provides-Extra: magic
Requires-Dist: python-magic-bin>=0.4.14; (sys_platform == 'win32') and extra == 'magic'
Requires-Dist: python-magic>=0.4.27; (sys_platform != 'win32') and extra == 'magic'
Provides-Extra: structlog
Requires-Dist: structlog>=23.1.0; extra == 'structlog'
Provides-Extra: test
Requires-Dist: pytest-asyncio>=0.21.0; extra == 'test'
Requires-Dist: pytest-cov>=4.1.0; extra == 'test'
Requires-Dist: pytest-mock>=3.11.0; extra == 'test'
Requires-Dist: pytest-timeout>=2.1.0; extra == 'test'
Requires-Dist: pytest>=7.4.0; extra == 'test'
